LICENSE.txt
MANIFEST.in
README.md
setup.cfg
setup.py
elena_pdf/__init__.py
elena_pdf/elena.py
elena_pdf.egg-info/PKG-INFO
elena_pdf.egg-info/SOURCES.txt
elena_pdf.egg-info/dependency_links.txt
elena_pdf.egg-info/requires.txt
elena_pdf.egg-info/top_level.txt
elena_pdf/poppler-21.01.0/Library/bin/cairo.dll
elena_pdf/poppler-21.01.0/Library/bin/freetype.dll
elena_pdf/poppler-21.01.0/Library/bin/libcrypto-1_1-x64.dll
elena_pdf/poppler-21.01.0/Library/bin/libcurl.dll
elena_pdf/poppler-21.01.0/Library/bin/liblzma.dll
elena_pdf/poppler-21.01.0/Library/bin/libpng16.dll
elena_pdf/poppler-21.01.0/Library/bin/libssh2.dll
elena_pdf/poppler-21.01.0/Library/bin/libtiff.dll
elena_pdf/poppler-21.01.0/Library/bin/libzstd.dll
elena_pdf/poppler-21.01.0/Library/bin/openjp2.dll
elena_pdf/poppler-21.01.0/Library/bin/pdfattach.exe
elena_pdf/poppler-21.01.0/Library/bin/pdfdetach.exe
elena_pdf/poppler-21.01.0/Library/bin/pdffonts.exe
elena_pdf/poppler-21.01.0/Library/bin/pdfimages.exe
elena_pdf/poppler-21.01.0/Library/bin/pdfinfo.exe
elena_pdf/poppler-21.01.0/Library/bin/pdfseparate.exe
elena_pdf/poppler-21.01.0/Library/bin/pdftocairo.exe
elena_pdf/poppler-21.01.0/Library/bin/pdftohtml.exe
elena_pdf/poppler-21.01.0/Library/bin/pdftoppm.exe
elena_pdf/poppler-21.01.0/Library/bin/pdftops.exe
elena_pdf/poppler-21.01.0/Library/bin/pdftotext.exe
elena_pdf/poppler-21.01.0/Library/bin/pdfunite.exe
elena_pdf/poppler-21.01.0/Library/bin/poppler-cpp.dll
elena_pdf/poppler-21.01.0/Library/bin/poppler-glib.dll
elena_pdf/poppler-21.01.0/Library/bin/poppler.dll
elena_pdf/poppler-21.01.0/Library/bin/tiff.dll
elena_pdf/poppler-21.01.0/Library/bin/zlib.dll
elena_pdf/poppler-21.01.0/Library/bin/zstd.dll
elena_pdf/poppler-21.01.0/Library/bin/zstd.exe
elena_pdf/poppler-21.01.0/Library/include/poppler/Annot.h
elena_pdf/poppler-21.01.0/Library/include/poppler/Array.h
elena_pdf/poppler-21.01.0/Library/include/poppler/BBoxOutputDev.h
elena_pdf/poppler-21.01.0/Library/include/poppler/CMap.h
elena_pdf/poppler-21.01.0/Library/include/poppler/CachedFile.h
elena_pdf/poppler-21.01.0/Library/include/poppler/CairoFontEngine.h
