Metadata-Version: 2.1
Name: elena-pdf
Version: 1.1.2
Summary: Manage pdf files: merge, split, convert to image and convert images to pdf
Home-page: UNKNOWN
Author: Dari Developer
Author-email: hernandezdarifrancisco@gmail.com
License: MIT
Project-URL: Documentation, https://github.com/DariHernandez/elena_pdf/blob/master/README.md
Project-URL: Funding, https://www.paypal.com/paypalme/FranciscoDari
Project-URL: Source, https://github.com/DariHernandez/elena_pdf
Keywords: elena,elena pdf,pdf,merge,split,convert to image,convert to pdfo,merge pdf,split pdf,convert pdf to image,convert image to pdf,pdf files,manage pdf
Platform: UNKNOWN
Requires-Python: >=3.7
